rhaid/__init__.py
rhaid/baseline.py
rhaid/cache.py
rhaid/cli.py
rhaid/config.py
rhaid/editorconfig.py
rhaid/js_rules.py
rhaid/jsonpatch.py
rhaid/logging_utils.py
rhaid/markdown_rules.py
rhaid/mdx_rules.py
rhaid/python_ast_rules.py
rhaid/rules.py
rhaid/scanner.py
rhaid/secrets.py
rhaid/terraform_rules.py
rhaid/toml_rules.py
rhaid-0.7.1.dist-info/licenses/LICENSE
rhaid-0.7.1.dist-info/METADATA
rhaid-0.7.1.dist-info/WHEEL
rhaid-0.7.1.dist-info/entry_points.txt
rhaid-0.7.1.dist-info/top_level.txt
rhaid-0.7.1.dist-info/RECORD
