Metadata-Version: 2.4
Name: rhaid
Version: 0.7.1
Summary: Rhaid Autofix — repo hygiene with smart AI guardrails
Author: Camwood Inc.
Requires-Python: >=3.9
License-File: LICENSE
Requires-Dist: PyYAML>=6.0.1
Requires-Dist: pathspec>=0.12.1
Requires-Dist: rich>=13.7.1
Requires-Dist: typer>=0.12.3
Provides-Extra: llm
Requires-Dist: openai>=1.30.0; extra == "llm"
Provides-Extra: hcl
Requires-Dist: python-hcl2>=4.3.3; extra == "hcl"
Provides-Extra: tomlkit
Requires-Dist: tomlkit>=0.12.0; extra == "tomlkit"
Dynamic: license-file
